{
  "profiles": {
    "front_fwd": {
      "engine": [0.35, 0.40, 0.00],
      "transmission": [0.30, 0.25, 0.00],
      "suspension": [-0.15, 0.20, 0.40],
      "brakes": [0.35, 0.15, 0.45],
      "exhaust": [-0.42, 0.12, 0.20],
      "tires-wheels": [-0.30, 0.15, 0.48],
      "air-intake": [0.30, 0.55, 0.00],
      "ecu-electronics": [0.05, 0.60, 0.15],
      "turbo-supercharger": [0.30, 0.35, 0.20],
      "fuel-system": [-0.30, 0.22, 0.25],
      "cooling-system": [0.45, 0.35, 0.00],
      "steering": [0.30, 0.25, 0.00]
    },
    "front_rwd": {
      "engine": [0.35, 0.40, 0.00],
      "transmission": [0.00, 0.20, 0.00],
      "suspension": [-0.15, 0.20, 0.40],
      "brakes": [0.35, 0.15, 0.45],
      "exhaust": [-0.42, 0.12, 0.20],
      "tires-wheels": [-0.30, 0.15, 0.48],
      "air-intake": [0.30, 0.55, 0.00],
      "ecu-electronics": [0.05, 0.60, 0.15],
      "turbo-supercharger": [0.30, 0.35, 0.20],
      "fuel-system": [-0.30, 0.22, 0.25],
      "cooling-system": [0.45, 0.35, 0.00],
      "steering": [0.30, 0.25, 0.00]
    },
    "front_awd": {
      "engine": [0.35, 0.40, 0.00],
      "transmission": [0.15, 0.22, 0.00],
      "suspension": [-0.15, 0.20, 0.40],
      "brakes": [0.35, 0.15, 0.45],
      "exhaust": [-0.42, 0.12, 0.20],
      "tires-wheels": [-0.30, 0.15, 0.48],
      "air-intake": [0.30, 0.55, 0.00],
      "ecu-electronics": [0.05, 0.60, 0.15],
      "turbo-supercharger": [0.30, 0.35, 0.20],
      "fuel-system": [-0.30, 0.22, 0.25],
      "cooling-system": [0.45, 0.35, 0.00],
      "steering": [0.30, 0.25, 0.00]
    },
    "mid_engine": {
      "engine": [-0.10, 0.35, 0.00],
      "transmission": [-0.20, 0.25, 0.00],
      "suspension": [-0.15, 0.20, 0.40],
      "brakes": [0.35, 0.15, 0.45],
      "exhaust": [-0.42, 0.12, 0.20],
      "tires-wheels": [-0.30, 0.15, 0.48],
      "air-intake": [-0.05, 0.55, 0.00],
      "ecu-electronics": [0.05, 0.60, 0.15],
      "turbo-supercharger": [-0.05, 0.35, 0.20],
      "fuel-system": [0.15, 0.22, 0.25],
      "cooling-system": [0.45, 0.35, 0.00],
      "steering": [0.30, 0.25, 0.00]
    },
    "rear_engine": {
      "engine": [-0.35, 0.35, 0.00],
      "transmission": [-0.25, 0.25, 0.00],
      "suspension": [-0.15, 0.20, 0.40],
      "brakes": [0.35, 0.15, 0.45],
      "exhaust": [-0.42, 0.12, 0.20],
      "tires-wheels": [-0.30, 0.15, 0.48],
      "air-intake": [-0.30, 0.55, 0.00],
      "ecu-electronics": [0.05, 0.60, 0.15],
      "turbo-supercharger": [-0.30, 0.35, 0.20],
      "fuel-system": [0.15, 0.22, 0.25],
      "cooling-system": [0.45, 0.35, 0.00],
      "steering": [0.30, 0.25, 0.00]
    },
    "electric": {
      "engine": [-0.30, 0.15, 0.00],
      "transmission": [-0.30, 0.12, 0.00],
      "suspension": [-0.15, 0.20, 0.40],
      "brakes": [0.35, 0.15, 0.45],
      "exhaust": null,
      "tires-wheels": [-0.30, 0.15, 0.48],
      "air-intake": null,
      "ecu-electronics": [0.05, 0.60, 0.15],
      "turbo-supercharger": null,
      "fuel-system": null,
      "cooling-system": [0.42, 0.25, 0.00],
      "steering": [0.30, 0.25, 0.00]
    },
    "electric_awd": {
      "engine": [0.30, 0.15, 0.00],
      "transmission": [-0.30, 0.15, 0.00],
      "suspension": [-0.15, 0.20, 0.40],
      "brakes": [0.35, 0.15, 0.45],
      "exhaust": null,
      "tires-wheels": [-0.30, 0.15, 0.48],
      "air-intake": null,
      "ecu-electronics": [0.05, 0.60, 0.15],
      "turbo-supercharger": null,
      "fuel-system": null,
      "cooling-system": [0.42, 0.25, 0.00],
      "steering": [0.30, 0.25, 0.00]
    }
  },
  "hidden_parts": {
    "electric": ["exhaust", "air-intake", "turbo-supercharger", "fuel-system"],
    "electric_awd": ["exhaust", "air-intake", "turbo-supercharger", "fuel-system"]
  },
  "layout_mapping": {
    "honda_civic": "front_fwd",
    "honda_accord": "front_fwd",
    "honda_cr-v": "front_fwd",
    "honda_hr-v": "front_fwd",
    "honda_pilot": "front_fwd",
    "honda_odyssey": "front_fwd",
    "honda_fit": "front_fwd",
    "toyota_camry": "front_fwd",
    "toyota_corolla": "front_fwd",
    "toyota_rav4": "front_fwd",
    "toyota_highlander": "front_fwd",
    "toyota_prius": "front_fwd",
    "toyota_tacoma": "front_rwd",
    "toyota_tundra": "front_rwd",
    "toyota_4runner": "front_rwd",
    "toyota_supra": "front_rwd",
    "toyota_gr86": "front_rwd",
    "hyundai_elantra": "front_fwd",
    "hyundai_sonata": "front_fwd",
    "hyundai_tucson": "front_fwd",
    "hyundai_santa fe": "front_fwd",
    "hyundai_kona": "front_fwd",
    "hyundai_ioniq 5": "electric_awd",
    "hyundai_ioniq 6": "electric_awd",
    "kia_forte": "front_fwd",
    "kia_k5": "front_fwd",
    "kia_sportage": "front_fwd",
    "kia_telluride": "front_fwd",
    "kia_ev6": "electric_awd",
    "kia_ev9": "electric_awd",
    "nissan_altima": "front_fwd",
    "nissan_sentra": "front_fwd",
    "nissan_rogue": "front_fwd",
    "nissan_pathfinder": "front_fwd",
    "nissan_frontier": "front_rwd",
    "nissan_370z": "front_rwd",
    "nissan_z": "front_rwd",
    "nissan_gt-r": "front_rwd",
    "nissan_leaf": "electric",
    "nissan_ariya": "electric_awd",
    "subaru_impreza": "front_fwd",
    "subaru_wrx": "front_fwd",
    "subaru_outback": "front_fwd",
    "subaru_forester": "front_fwd",
    "subaru_crosstrek": "front_fwd",
    "subaru_brz": "front_rwd",
    "mazda_mazda3": "front_fwd",
    "mazda_cx-5": "front_fwd",
    "mazda_cx-30": "front_fwd",
    "mazda_mx-5 miata": "front_rwd",
    "bmw_3 series": "front_rwd",
    "bmw_4 series": "front_rwd",
    "bmw_5 series": "front_rwd",
    "bmw_7 series": "front_rwd",
    "bmw_x3": "front_rwd",
    "bmw_x5": "front_rwd",
    "bmw_m3": "front_rwd",
    "bmw_m4": "front_rwd",
    "bmw_i4": "electric",
    "bmw_ix": "electric_awd",
    "mercedes-benz_c-class": "front_rwd",
    "mercedes-benz_e-class": "front_rwd",
    "mercedes-benz_s-class": "front_rwd",
    "mercedes-benz_glc": "front_rwd",
    "mercedes-benz_gle": "front_rwd",
    "mercedes-benz_amg gt": "front_rwd",
    "mercedes-benz_eqe": "electric",
    "mercedes-benz_eqs": "electric_awd",
    "audi_a4": "front_fwd",
    "audi_a6": "front_fwd",
    "audi_q5": "front_fwd",
    "audi_q7": "front_fwd",
    "audi_rs3": "front_fwd",
    "audi_e-tron": "electric_awd",
    "audi_e-tron gt": "electric_awd",
    "ford_f-150": "front_rwd",
    "ford_f-250": "front_rwd",
    "ford_mustang": "front_rwd",
    "ford_bronco": "front_rwd",
    "ford_explorer": "front_rwd",
    "ford_escape": "front_fwd",
    "ford_focus": "front_fwd",
    "ford_fusion": "front_fwd",
    "ford_maverick": "front_fwd",
    "ford_mustang mach-e": "electric_awd",
    "ford_f-150 lightning": "electric_awd",
    "chevrolet_silverado": "front_rwd",
    "chevrolet_camaro": "front_rwd",
    "chevrolet_corvette": "mid_engine",
    "chevrolet_malibu": "front_fwd",
    "chevrolet_equinox": "front_fwd",
    "chevrolet_tahoe": "front_rwd",
    "chevrolet_suburban": "front_rwd",
    "chevrolet_bolt": "electric",
    "chevrolet_blazer ev": "electric_awd",
    "dodge_challenger": "front_rwd",
    "dodge_charger": "front_rwd",
    "dodge_durango": "front_rwd",
    "ram_1500": "front_rwd",
    "ram_2500": "front_rwd",
    "gmc_sierra": "front_rwd",
    "gmc_yukon": "front_rwd",
    "gmc_canyon": "front_rwd",
    "gmc_hummer ev": "electric_awd",
    "jeep_wrangler": "front_rwd",
    "jeep_grand cherokee": "front_rwd",
    "jeep_cherokee": "front_fwd",
    "jeep_gladiator": "front_rwd",
    "tesla_model 3": "electric_awd",
    "tesla_model y": "electric_awd",
    "tesla_model s": "electric_awd",
    "tesla_model x": "electric_awd",
    "tesla_cybertruck": "electric_awd",
    "rivian_r1t": "electric_awd",
    "rivian_r1s": "electric_awd",
    "porsche_911": "rear_engine",
    "porsche_cayman": "mid_engine",
    "porsche_boxster": "mid_engine",
    "porsche_718 cayman": "mid_engine",
    "porsche_718 boxster": "mid_engine",
    "porsche_cayenne": "front_rwd",
    "porsche_macan": "front_rwd",
    "porsche_taycan": "electric_awd",
    "volkswagen_golf": "front_fwd",
    "volkswagen_jetta": "front_fwd",
    "volkswagen_tiguan": "front_fwd",
    "volkswagen_id.4": "electric_awd",
    "lexus_is": "front_rwd",
    "lexus_es": "front_fwd",
    "lexus_rx": "front_fwd",
    "lexus_nx": "front_fwd",
    "acura_integra": "front_fwd",
    "acura_tlx": "front_fwd",
    "acura_mdx": "front_fwd",
    "infiniti_q50": "front_rwd",
    "infiniti_q60": "front_rwd",
    "genesis_g70": "front_rwd",
    "genesis_g80": "front_rwd",
    "genesis_gv70": "front_rwd",
    "alfa romeo_giulia": "front_rwd",
    "alfa romeo_stelvio": "front_rwd",
    "alfa romeo_4c": "mid_engine",
    "cadillac_escalade": "front_rwd",
    "cadillac_ct4": "front_rwd",
    "cadillac_ct5": "front_rwd",
    "cadillac_xt4": "front_fwd",
    "cadillac_xt5": "front_fwd",
    "cadillac_xt6": "front_fwd",
    "cadillac_lyriq": "electric_awd",
    "chrysler_300": "front_rwd",
    "chrysler_pacifica": "front_fwd",
    "buick_enclave": "front_fwd",
    "buick_envision": "front_fwd",
    "buick_encore gx": "front_fwd",
    "lincoln_navigator": "front_rwd",
    "lincoln_aviator": "front_rwd",
    "lincoln_corsair": "front_fwd",
    "lincoln_nautilus": "front_fwd",
    "volvo_xc60": "front_awd",
    "volvo_xc90": "front_awd",
    "volvo_s60": "front_fwd",
    "volvo_xc40": "front_fwd",
    "volvo_v60": "front_fwd",
    "volvo_c40": "electric",
    "jaguar_f-type": "front_rwd",
    "jaguar_f-pace": "front_rwd",
    "jaguar_e-pace": "front_fwd",
    "jaguar_i-pace": "electric_awd",
    "jaguar_xe": "front_rwd",
    "jaguar_xf": "front_rwd",
    "land rover_range rover": "front_awd",
    "land rover_range rover sport": "front_awd",
    "land rover_defender": "front_awd",
    "land rover_discovery": "front_awd",
    "land rover_evoque": "front_awd",
    "maserati_ghibli": "front_rwd",
    "maserati_levante": "front_rwd",
    "maserati_mc20": "mid_engine",
    "maserati_quattroporte": "front_rwd",
    "maserati_grecale": "front_rwd",
    "mclaren_720s": "mid_engine",
    "mclaren_750s": "mid_engine",
    "mclaren_artura": "mid_engine",
    "mclaren_gt": "mid_engine",
    "lamborghini_huracan": "mid_engine",
    "lamborghini_urus": "front_awd",
    "lamborghini_aventador": "mid_engine",
    "lamborghini_revuelto": "mid_engine",
    "ferrari_296 gtb": "mid_engine",
    "ferrari_f8 tributo": "mid_engine",
    "ferrari_sf90": "mid_engine",
    "ferrari_roma": "front_rwd",
    "ferrari_812": "front_rwd",
    "ferrari_purosangue": "front_rwd",
    "aston martin_db11": "front_rwd",
    "aston martin_vantage": "front_rwd",
    "aston martin_dbs": "front_rwd",
    "aston martin_dbx": "front_awd",
    "bentley_continental gt": "front_awd",
    "bentley_bentayga": "front_awd",
    "bentley_flying spur": "front_awd",
    "rolls-royce_phantom": "front_rwd",
    "rolls-royce_ghost": "front_rwd",
    "rolls-royce_cullinan": "front_awd",
    "rolls-royce_spectre": "electric_awd",
    "lotus_emira": "mid_engine",
    "lotus_evija": "electric_awd",
    "lotus_eletre": "electric_awd",
    "mini_cooper": "front_fwd",
    "mini_countryman": "front_fwd",
    "mini_clubman": "front_fwd",
    "fiat_500": "front_fwd",
    "fiat_500x": "front_fwd",
    "mitsubishi_outlander": "front_awd",
    "mitsubishi_eclipse cross": "front_fwd",
    "mitsubishi_mirage": "front_fwd",
    "suzuki_jimny": "front_rwd",
    "suzuki_swift": "front_fwd",
    "suzuki_vitara": "front_fwd",
    "polestar_polestar 2": "electric_awd",
    "polestar_polestar 3": "electric_awd",
    "lucid_air": "electric_awd",
    "lucid_gravity": "electric_awd"
  }
}
